huniutils/__init__.py
huniutils/__main__.py
huniutils/manage_os.py
huniutils/read_save.py
huniutils/measurement/__init__.py
huniutils/measurement/ctt.py
huni_utils-0.1.5.dist-info/LICENSE
huni_utils-0.1.5.dist-info/METADATA
huni_utils-0.1.5.dist-info/WHEEL
huni_utils-0.1.5.dist-info/entry_points.txt
huni_utils-0.1.5.dist-info/top_level.txt
huni_utils-0.1.5.dist-info/RECORD
