Metadata-Version: 2.1
Name: huni-utils
Version: 0.1.5
Summary: frequently used utilities
Author-email: JeeHun Sung <jhun1023@naver.com>
License: MIT License
Project-URL: Homepage, https://github.com/huni1023/huni-utils
Requires-Python: >=3.8
License-File: LICENSE
Requires-Dist: PyYaml
Requires-Dist: pandas
Requires-Dist: numpy
